Workbook

Sheet README
A1: Municipality Preparedness Index – Indicator Catalogue
A3: Purpose | B3: This workbook converts the exhaustive indicator longlist into a structured spreadsheet for developing a Municipality Preparedness Index supporting total preparedness.
A4: Compared with uploaded article | B4: The uploaded Norwegian BRIC adaptation is a structural community-resilience baseline. This catalogue keeps structural indicators as context, but adds municipal preparedness, continuity, coordination, logistics, total-defence/profile, learning and validation indicators.
A5: Recommended use | B5: Use Indicator_Longlist as the master registry; filter by Feasibility and Candidate tier to identify indicators for a Core MPI, Extended MPI, profile modules, and validation indicators.
A6: Do not publish sensitive data | B6: Total-defence, military-hosting, infrastructure-owner redundancy, and detailed service-continuity indicators may need aggregation or restricted handling.
A7: Suggested first reduction | B7: Start with 30–40 indicators: mostly Core candidate + Extended candidate, with a limited number of high-value municipal-document indicators.
A9: Sheets | B9: Description
A10: Indicator_Longlist | B10: 253 indicators with domain, metric, source, feasibility and candidate tier.
A11: Core_MPI_Draft | B11: A draft reduced subset of high-value indicators that could be considered for an initial core index.

Sheet Summary
A1: Municipality Preparedness Index – Indicator Catalogue Summary
A3: Total indicators in longlist: 253
A6: Dimension | B6: Indicator count
A7: Risk and threat intelligence | B7: =COUNTIF(Indicator_Longlist!$A$2:$A$254,A7) -> 25
A8: Governance and crisis-management capacity | B8: =COUNTIF(Indicator_Longlist!$A$2:$A$254,A8) -> 28
A9: Total defence and security-crisis support | B9: =COUNTIF(Indicator_Longlist!$A$2:$A$254,A9) -> 10
A10: Continuity of critical municipal services | B10: =COUNTIF(Indicator_Longlist!$A$2:$A$254,A10) -> 32
A11: Supply, logistics and resource mobilisation | B11: =COUNTIF(Indicator_Longlist!$A$2:$A$254,A11) -> 20
A12: Population protection and crisis communication | B12: =COUNTIF(Indicator_Longlist!$A$2:$A$254,A12) -> 25
A13: Exercises, learning and tested capability | B13: =COUNTIF(Indicator_Longlist!$A$2:$A$254,A13) -> 20
A14: Structural capacity and vulnerability baseline | B14: =COUNTIF(Indicator_Longlist!$A$2:$A$254,A14) -> 47
A15: Small and low-capacity municipalities | B15: =COUNTIF(Indicator_Longlist!$A$2:$A$254,A15) -> 8
A16: Coastal and island municipalities | B16: =COUNTIF(Indicator_Longlist!$A$2:$A$254,A16) -> 10
A17: Military-hosting municipalities | B17: =COUNTIF(Indicator_Longlist!$A$2:$A$254,A17) -> 8
A18: Critical-infrastructure / major-industry municipalities | B18: =COUNTIF(Indicator_Longlist!$A$2:$A$254,A18) -> 10
A19: Validation and outcome indicators | B19: =COUNTIF(Indicator_Longlist!$A$2:$A$254,A19) -> 10
A22: Feasibility code | B22: Indicator count
A23: A | B23: =COUNTIF(Indicator_Longlist!$F$2:$F$254,A23) -> 31
A24: A/B | B24: =COUNTIF(Indicator_Longlist!$F$2:$F$254,A24) -> 25
A25: B | B25: =COUNTIF(Indicator_Longlist!$F$2:$F$254,A25) -> 96
A26: B/C | B26: =COUNTIF(Indicator_Longlist!$F$2:$F$254,A26) -> 13
A27: C | B27: =COUNTIF(Indicator_Longlist!$F$2:$F$254,A27) -> 54
A28: C/P | B28: =COUNTIF(Indicator_Longlist!$F$2:$F$254,A28) -> 26
A29: B/P | B29: =COUNTIF(Indicator_Longlist!$F$2:$F$254,A29) -> 6
A30: P | B30: =COUNTIF(Indicator_Longlist!$F$2:$F$254,A30) -> 1
A31: A/B/P | B31: =COUNTIF(Indicator_Longlist!$F$2:$F$254,A31) -> 1
A34: Candidate tier | B34: Indicator count
A35: Core candidate | B35: =COUNTIF(Indicator_Longlist!$G$2:$G$254,A35) -> 16
A36: Extended candidate | B36: =COUNTIF(Indicator_Longlist!$G$2:$G$254,A36) -> 91
A37: Restricted/municipal data | B37: =COUNTIF(Indicator_Longlist!$G$2:$G$254,A37) -> 31
A38: Profile/pilot | B38: =COUNTIF(Indicator_Longlist!$G$2:$G$254,A38) -> 12
A39: Profile/pilot/restricted | B39: =COUNTIF(Indicator_Longlist!$G$2:$G$254,A39) -> 46
A40: Baseline/context | B40: =COUNTIF(Indicator_Longlist!$G$2:$G$254,A40) -> 47
A41: Validation/outcome | B41: =COUNTIF(Indicator_Longlist!$G$2:$G$254,A41) -> 10

Sheet Indicator_Longlist
A1: Dimension | B1: Subdimension | C1: Indicator ID | D1: Indicator | E1: Possible metric | F1: Feasibility | G1: Candidate tier
A2: Risk and threat intelligence | B2: Risk and threat intelligence | C2: RISK-01 | D2: Updated holistic ROS | E2: Years since last overall municipal ROS | F2: A | G2: Core candidate
A3: Risk and threat intelligence | B3: Risk and threat intelligence | C3: RISK-02 | D3: ROS formally adopted | E3: Yes/no; year of political adoption | F3: A/B | G3: Core candidate
A4: Risk and threat intelligence | B4: Risk and threat intelligence | C4: RISK-03 | D4: ROS revision routine | E4: Annual/periodic review documented | F4: B | G4: Extended candidate
A5: Risk and threat intelligence | B5: Risk and threat intelligence | C5: RISK-04 | D5: Climate-risk inclusion | E5: Climate scenarios included in ROS | F5: B | G5: Extended candidate
A6: Risk and threat intelligence | B6: Risk and threat intelligence | C6: RISK-05 | D6: Flood-risk inclusion | E6: Flood scenario or flood-zone exposure included | F6: A/B | G6: Core candidate
A7: Risk and threat intelligence | B7: Risk and threat intelligence | C7: RISK-06 | D7: Landslide/avalanche-risk inclusion | E7: Landslide/snow-avalanche scenario included | F7: A/B | G7: Core candidate
A8: Risk and threat intelligence | B8: Risk and threat intelligence | C8: RISK-07 | D8: Storm-surge/coastal-risk inclusion | E8: Included where relevant | F8: B/P | G8: Profile/pilot
A9: Risk and threat intelligence | B9: Risk and threat intelligence | C9: RISK-08 | D9: Wildfire-risk inclusion | E9: Wildfire scenario included | F9: B | G9: Extended candidate
A10: Risk and threat intelligence | B10: Risk and threat intelligence | C10: RISK-09 | D10: Long power-outage scenario | E10: Scenario for prolonged electricity loss | F10: B | G10: Extended candidate
A11: Risk and threat intelligence | B11: Risk and threat intelligence | C11: RISK-10 | D11: ICT failure scenario | E11: Scenario for municipal ICT outage | F11: B | G11: Extended candidate
A12: Risk and threat intelligence | B12: Risk and threat intelligence | C12: RISK-11 | D12: Cyberattack scenario | E12: Cyberattack included in ROS or ICT contingency plan | F12: B/C | G12: Extended candidate
... A254: Validation and outcome indicators | B254: Validation and outcome indicators | C254: VAL-10 | D254: External expert assessment | E254: Audit/panel score | F254: C/P | G254: Validation/outcome

Sheet Core_MPI_Draft
A1: Dimension | B1: Subdimension | C1: Indicator ID | D1: Indicator | E1: Candidate tier
A2: Risk and threat intelligence | B2: Risk and threat intelligence | C2: RISK-01 | D2: Updated holistic ROS | E2: Core candidate
A3: Risk and threat intelligence | B3: Risk and threat intelligence | C3: RISK-04 | D3: Climate-risk inclusion | E3: Extended candidate
A4: Risk and threat intelligence | B4: Risk and threat intelligence | C4: RISK-09 | D4: Long power-outage scenario | E4: Extended candidate
A5: Risk and threat intelligence | B5: Risk and threat intelligence | C5: RISK-10 | D5: ICT failure scenario | E5: Extended candidate
A6: Risk and threat intelligence | B6: Risk and threat intelligence | C6: RISK-12 | D6: E-com outage scenario | E6: Extended candidate
A7: Risk and threat intelligence | B7: Risk and threat intelligence | C7: RISK-18 | D7: Cascading-risk analysis | E7: Extended candidate
A8: Risk and threat intelligence | B8: Risk and threat intelligence | C8: RISK-21 | D8: Vulnerable-group mapping | E8: Extended candidate
A9: Governance and crisis-management capacity | B9: Governance and crisis-management capacity | C9: GOV-02 | D9: Crisis management team established | E9: Core candidate
A10: Governance and crisis-management capacity | B10: Governance and crisis-management capacity | C10: GOV-04 | D10: Municipal emergency plan updated | E10: Core candidate
A11: Governance and crisis-management capacity | B11: Governance and crisis-management capacity | C11: GOV-11 | D11: 24/7 alerting arrangement | E11: Extended candidate
A12: Governance and crisis-management capacity | B12: Governance and crisis-management capacity | C12: GOV-17 | D12: Preparedness council established | E12: Core candidate
... A44: Exercises, learning and tested capability | B44: Exercises, learning and tested capability | C44: LEARN-16 | D44: Lessons incorporated into ROS/plan | E44: Extended candidate

Sheet Source_Glossary
A1: Source code | B1: Description | C1: Example URL | D1: Access / use notes
A2: SSB / StatBank | B2: Statistics Norway statistical tables and API | C2: https://www.ssb.no/en/api/pxwebapi | D2: Municipal demographic, social, economic, health and service indicators.
A3: KOSTRA | B3: Municipality-state reporting through Statistics Norway | C3: https://www.ssb.no/en/offentlig-sektor/kostra/statistikk/kostra-kommune-stat-rapportering | D3: Municipal service, finance, health/care, water/wastewater and fire-related data.
A4: DSB Kommuneundersøkelsen | B4: DSB municipal preparedness survey | C4: https://www.dsb.no/ros-og-beredskap/kommuner/kommuneundersokelsen/ | D4: Useful for ROS, emergency plans, exercises, preparedness councils and municipal preparedness duty.
A5: DSB municipal preparedness | B5: DSB municipal safety and preparedness resources | C5: https://www.dsb.no/ros-og-beredskap/kommuner/ | D5: Guidance, regulations, and context for municipal emergency planning.
A6: Geonorge | B6: Norwegian national geodata portal and APIs | C6: https://www.geonorge.no/en/for-developers/apis/ | D6: Metadata and geodata services for spatial indicators.
A7: Kartverket | B7: Norwegian Mapping Authority | C7: https://www.kartverket.no/en | D7: Base maps, administrative boundaries and geospatial data.
A8: NVE map services | B8: Norwegian Water Resources and Energy Directorate map services | C8: https://www.nve.no/map-services/ | D8: Flood, landslide, avalanche and hydrology map services.
A9: NVE Regobs API | B9: Observation data for natural hazards | C9: https://api.nve.no/doc/regobs/ | D9: Warnings/observations supporting hazard-frequency and monitoring indicators.
A10: Statens vegvesen / NVDB | B10: Road data and traffic datasets | C10: https://dataut.vegvesen.no/ | D10: Road network, access, traffic and road safety indicators.
A11: SVV traffic data | B11: Traffic data from public roads | C11: https://dataut.vegvesen.no/en/dataset/trafikkdata | D11: Useful for traffic and transport robustness indicators.
A12: Nkom | B12: Norwegian Communications Authority | C12: https://nkom.no/ | D12: Broadband, mobile and electronic communications indicators.
... A24: Voluntary organisations | B24: Red Cross, Norsk Folkehjelp, faith/community groups, local organisations | C24: Not a single URL | D24: Agreements, mobilisation and resource indicators.

Sheet Feasibility_Legend
A1: Code | B1: Meaning | C1: Recommended use
A2: A | B2: High feasibility: likely available nationally from open or semi-open data. | C2: Use for Core MPI when conceptually relevant.
A3: A/B | B3: High to medium feasibility: likely open data or straightforward municipal/DSB source. | C3: Use for Core MPI or first extension.
A4: B | B4: Medium feasibility: likely available through DSB survey, municipal documents, or a simple municipal survey. | C4: Use for Extended MPI or document-review version.
A5: B/C | B5: Medium to low feasibility: may require document review, municipal self-assessment, or restricted partner input. | C5: Use selectively; avoid overloading Core MPI.
A6: C | B6: Low open-data feasibility: needs municipal self-assessment, infrastructure-owner input, restricted data, or detailed document review. | C6: Use in pilots, restricted module, or aggregated maturity score.
A7: B/P | B7: Medium feasibility but profile-specific. | C7: Use only for relevant municipality types.
A8: C/P | B8: Low open-data feasibility and profile/sensitivity-specific. | C8: Use in profile modules or living labs; do not publish raw details.
A9: P | B9: Pilot/profile indicator, not intended for all municipalities. | C9: Use only in relevant profiles or living labs.
A11: Evidence level | B11: Meaning | C11: Recommended interpretation
A12: A-evidence | B12: Open quantitative data | C12: Most comparable nationally.
A13: B-evidence | B13: Document verified | C13: Good if scoring protocol is consistent.
... A17: R-evidence | B17: Restricted/sensitive source | C17: Use aggregated or internal-only scoring.
